django_byo_react/__init__.py
django_byo_react/apps.py
django_byo_react/templates/django_byo_react/includes/byo_react.html
django_byo_react/templatetags/__init__.py
django_byo_react/templatetags/byo_react.py
django_byo_react-1.0.0.dist-info/METADATA
django_byo_react-1.0.0.dist-info/WHEEL
django_byo_react-1.0.0.dist-info/licenses/LICENSE
django_byo_react-1.0.0.dist-info/RECORD
