Metadata-Version: 2.3
Name: django-byo-react
Version: 1.0.0
Summary: A template tag to create a div and json script tag for react to bind to
Project-URL: Repository, https://github.com/lukewiwa/django-byo-react
Author-email: lukewiwa <luke.wiwa@gmail.com>
License: MIT License
License-File: LICENSE
Classifier: Framework :: Django
Classifier: License :: OSI Approved :: MIT License
Classifier: Operating System :: OS Independent
Classifier: Programming Language :: Python :: 3
Requires-Python: >=3.9
Requires-Dist: django>=4.2
